{
    "m_Version": 12,
    "DisplayName": "CARS",
    "Icon": "Deliver",
    "Color": "FBFCFEFF",
    "IsExchange": 0,
    "InitStockPercent": 10.0,
    "Items": [
        {
            "ClassName": "AZLK_rust",
            "MaxPriceThreshold": 35000,
            "MinPriceThreshold": 24000,
            "SellPricePercent": -75.0,
            "MaxStockThreshold": 1,
            "MinStockThreshold": 1,
            "QuantityPercent": -1,
            "SpawnAttachments": [
                "AZLK_Wheel",
                "AZLK_Wheel",
                "AZLK_Wheel",
                "AZLK_Wheel",
                "AZLK_Wheel",
                "carbattery",
                "carradiator",
                "sparkplug",
                "AZLK_Doors_Driver_rust",
                "AZLK_Doors_coDriver_rust",
                "AZLK_Doors_cargo1_rust",
                "AZLK_Doors_cargo2_rust",
                "AZLK_Doors_hood_rust",
                "AZLK_Doors_trunk_rust",
                "headlighth7",
                "headlighth7"
            ],
            "Variants": []
        },
        {
            "ClassName": "Interceptor",
            "MaxPriceThreshold": 58000,
            "MinPriceThreshold": 50000,
            "SellPricePercent": -75.0,
            "MaxStockThreshold": 1,
            "MinStockThreshold": 1,
            "QuantityPercent": -1,
            "SpawnAttachments": [
                "Interceptor_Wheel",
                "Interceptor_Wheel",
                "Interceptor_Wheel",
                "Interceptor_Wheel",
                "Interceptor_Wheel",
                "carbattery",
                "carradiator",
                "sparkplug",
                "Interceptor_Doors_Driver",
                "Interceptor_Doors_coDriver",
                "Interceptor_Doors_hood",
                "headlighth7",
                "headlighth7"
            ],
            "Variants": []
        },
        {
            "ClassName": "MUSTANG_rust",
            "MaxPriceThreshold": 120000,
            "MinPriceThreshold": 100000,
            "SellPricePercent": -75.0,
            "MaxStockThreshold": 1,
            "MinStockThreshold": 1,
            "QuantityPercent": -1,
            "SpawnAttachments": [
                "MUSTANG_Wheel",
                "MUSTANG_Wheel",
                "MUSTANG_Wheel",
                "MUSTANG_Wheel",
                "MUSTANG_Wheel",
                "carbattery",
                "carradiator",
                "MUSTANG_Doors_Driver_rust",
                "MUSTANG_Doors_coDriver_rust",
                "MUSTANG_Doors_hood_rust",
                "MUSTANG_Doors_trunk_rust",
                "headlighth7",
                "headlighth7"
            ],
            "Variants": []
        },
        {
            "ClassName": "BMW_rust",
            "MaxPriceThreshold": 260000,
            "MinPriceThreshold": 240000,
            "SellPricePercent": -75.0,
            "MaxStockThreshold": 1,
            "MinStockThreshold": 1,
            "QuantityPercent": -1,
            "SpawnAttachments": [
                "BMW_Wheel",
                "BMW_Wheel",
                "BMW_Wheel",
                "BMW_Wheel",
                "BMW_Wheel",
                "headlighth7",
                "headlighth7",
                "BMW_Doors_trunk_white_rust",
                "carbattery",
                "carradiator",
                "sparkplug",
                "BMW_Doors_Driver_white_rust",
                "BMW_Doors_coDriver_white_rust",
                "BMW_Doors_cargo1_white_rust",
                "BMW_Doors_cargo2_white_rust",
                "BMW_Doors_hood_white_rust"
            ],
            "Variants": []
        },
        {
            "ClassName": "MBw140_black",
            "MaxPriceThreshold": 150000,
            "MinPriceThreshold": 150000,
            "SellPricePercent": -75.0,
            "MaxStockThreshold": 1,
            "MinStockThreshold": 1,
            "QuantityPercent": -1,
            "SpawnAttachments": [
                "MBw140_Wheel",
                "MBw140_Wheel",
                "MBw140_Wheel",
                "MBw140_Wheel",
                "MBw140_Wheel",
                "MBw140_Doors_trunk_black",
                "MBw140_Doors_hood_black",
                "carbattery",
                "carradiator",
                "sparkplug",
                "headlighth7",
                "headlighth7",
                "MBw140_Doors_cargo2_black",
                "MBw140_Doors_cargo1_black",
                "MBw140_Doors_coDriver_black",
                "MBw140_Doors_Driver_black"
            ],
            "Variants": []
        },
        {
            "ClassName": "Audi_RS6_white",
            "MaxPriceThreshold": 75000,
            "MinPriceThreshold": 75000,
            "SellPricePercent": -75.0,
            "MaxStockThreshold": 1,
            "MinStockThreshold": 1,
            "QuantityPercent": -1,
            "SpawnAttachments": [
                "Audi_RS6_Doors_Driver_white",
                "Audi_RS6_Doors_coDriver_white",
                "Audi_RS6_Doors_cargo1_white",
                "Audi_RS6_Doors_cargo2_white",
                "Audi_RS6_Doors_hood_white",
                "Audi_RS6_Wheel",
                "Audi_RS6_Wheel",
                "carbattery",
                "carradiator",
                "sparkplug",
                "headlighth7",
                "headlighth7",
                "Audi_RS6_Wheel",
                "Audi_RS6_Wheel",
                "Audi_RS6_Wheel"
            ],
            "Variants": []
        },
        {
            "ClassName": "Buggy",
            "MaxPriceThreshold": 55000,
            "MinPriceThreshold": 55000,
            "SellPricePercent": -75.0,
            "MaxStockThreshold": 1,
            "MinStockThreshold": 1,
            "QuantityPercent": -1,
            "SpawnAttachments": [
                "Buggy_Doors_Driver",
                "Buggy_Doors_coDriver",
                "carbattery",
                "carradiator",
                "sparkplug",
                "headlighth7",
                "headlighth7",
                "Buggy_Wheel_offroad",
                "Buggy_Wheel_offroad",
                "Buggy_Wheel_offroad",
                "Buggy_Wheel_offroad",
                "Buggy_Wheel_offroad"
            ],
            "Variants": []
        },
        {
            "ClassName": "Chevrolet_Camaro",
            "MaxPriceThreshold": 265000,
            "MinPriceThreshold": 265000,
            "SellPricePercent": -75.0,
            "MaxStockThreshold": 1,
            "MinStockThreshold": 1,
            "QuantityPercent": -1,
            "SpawnAttachments": [
                "Chevrolet_Camaro_Doors_Driver",
                "Chevrolet_Camaro_Doors_coDriver",
                "Chevrolet_Camaro_Doors_hood",
                "Chevrolet_Camaro_Doors_trunk",
                "carbattery",
                "carradiator",
                "sparkplug",
                "headlighth7",
                "headlighth7",
                "Chevrolet_Camaro_Wheel",
                "Chevrolet_Camaro_Wheel",
                "Chevrolet_Camaro_Wheel",
                "Chevrolet_Camaro_Wheel",
                "Chevrolet_Camaro_Wheel"
            ],
            "Variants": []
        },
        {
            "ClassName": "Opel_Astra",
            "MaxPriceThreshold": 65000,
            "MinPriceThreshold": 65000,
            "SellPricePercent": -75.0,
            "MaxStockThreshold": 1,
            "MinStockThreshold": 1,
            "QuantityPercent": -1,
            "SpawnAttachments": [
                "Opel_Astra_Doors_Driver",
                "Opel_Astra_Doors_coDriver",
                "Opel_Astra_Doors_cargo2",
                "Opel_Astra_Doors_cargo1",
                "Opel_Astra_Doors_hood",
                "Opel_Astra_Doors_trunk",
                "carbattery",
                "carradiator",
                "sparkplug",
                "headlighth7",
                "headlighth7",
                "Opel_Astra_Wheel",
                "Opel_Astra_Wheel",
                "Opel_Astra_Wheel",
                "Opel_Astra_Wheel",
                "Opel_Astra_Wheel"
            ],
            "Variants": []
        },
        {
            "ClassName": "PONTIAC_rust",
            "MaxPriceThreshold": 105000,
            "MinPriceThreshold": 105000,
            "SellPricePercent": -75.0,
            "MaxStockThreshold": 1,
            "MinStockThreshold": 1,
            "QuantityPercent": -1,
            "SpawnAttachments": [
                "PONTIAC_Doors_Driver_rust",
                "PONTIAC_Doors_coDriver_rust",
                "PONTIAC_Doors_hood_rust",
                "PONTIAC_Doors_trunk_rust",
                "carbattery",
                "carradiator",
                "sparkplug",
                "headlighth7",
                "headlighth7",
                "PONTIAC_Wheel",
                "PONTIAC_Wheel",
                "PONTIAC_Wheel",
                "PONTIAC_Wheel",
                "PONTIAC_Wheel"
            ],
            "Variants": []
        }
    ]
}